oztimur_probability/Binomialdistribution.py
oztimur_probability/Gaussiandistribution.py
oztimur_probability/Generaldistribution.py
oztimur_probability/__init__.py
oztimur_probability-0.3.dist-info/METADATA
oztimur_probability-0.3.dist-info/WHEEL
oztimur_probability-0.3.dist-info/top_level.txt
oztimur_probability-0.3.dist-info/RECORD
