Metadata-Version: 2.1
Name: oztimur-probability
Version: 0.3
Summary: Gaussian and Binomial distributions
Author: Irem Oztimur
Author-email: iremoztimur@gmail.com
